DemoConecteseSigPy/ArcGISPythonApiDataAccess.py
DemoConecteseSigPy/ArcGISRestApiDataAccess.py
DemoConecteseSigPy/ArcpyDataAccess.py
DemoConecteseSigPy/DataAccess.py
DemoConecteseSigPy/Estadisticas.py
DemoConecteseSigPy/Herramientas.py
DemoConecteseSigPy/Utiles.py
DemoConecteseSigPy/__init__.py
DemoConecteseSigPy/createtoolboxsupportfiles.py
DemoConecteseSigPy/esri/arcpy/DemoConecteseSig.py
DemoConecteseSigPy/esri/help/gp/ActualizarFechas_DemoConecteseSigPy.xml
DemoConecteseSigPy/esri/help/gp/DemoConecteseSigPy_toolbox.xml
DemoConecteseSigPy/esri/help/gp/toolboxes/DemoConecteseSig.xml
DemoConecteseSigPy/esri/toolboxes/DemoConecteseSig.ActualizarFechas.pyt.xml
DemoConecteseSigPy/esri/toolboxes/DemoConecteseSig.pyt
DemoConecteseSigPy/esri/toolboxes/DemoConecteseSig.pyt.xml
DemoConecteseSigPy-0.0.0.2.dist-info/METADATA
DemoConecteseSigPy-0.0.0.2.dist-info/WHEEL
DemoConecteseSigPy-0.0.0.2.dist-info/top_level.txt
DemoConecteseSigPy-0.0.0.2.dist-info/RECORD
