Metadata-Version: 2.1
Name: DemoConecteseSigPy
Version: 0.0.0.2
Summary: Herramientas Demostración para el Conectese con SIG - ArcGIS Pro.
Home-page: https://github.com/marceloctorres/DemoConecteseSigPython
Author: Esri Colombia
Author-email: mtorres@esri.co
License: MIT
Classifier: Programming Language :: Python :: 3.6
Classifier: License :: OSI Approved :: MIT License
Classifier: Operating System :: Microsoft :: Windows :: Windows 10
Classifier: Operating System :: MacOS
Classifier: Operating System :: Other OS
Classifier: Natural Language :: Spanish
Requires-Python: >=3.6.10
